{"name":"Trọng Sinh Về Tôi Chỉ Muốn Được Nghỉ Ngơi","folder":"trongsinhvetoichimuondjuocnghingoi","tacGia":"AkiSorl","theLoai":"Tiên Hiệp","trangThai":"Đang ra","description":"Truyện \"Trọng Sinh Về Tôi Chỉ Muốn Được Nghỉ Ngơi\" của tác giả AkiSorl xoay quanh nhân vật Ninh Nguyên - một thiên tài của tông môn đứng đầu trong thập đại tông môn ở trung châu đại lục. Với nỗ lực và cố gắng trong tu hành, cậu có cơ phi thăng cao hơn.<br><br>Tuy nhiên, cuộc đời không như mơ, khi Ninh Nguyên đem lòng yêu những thiên tài khác cùng tông môn. Tình yêu đã làm lu mờ cậu, và cậu đã làm mọi thứ vì những người đó. Nhưng cuối cùng, tình yêu của cậu chỉ được đáp lại bằng sự lạnh lùng và không quan tâm, và người mà cậu yêu thì lại đem lòng yêu một người khác.<br><br>Cuối cùng, tình yêu đã đẩy Ninh Nguyên đến cái chết. Nếu bạn là một fan của truyện đam mỹ, chắc chắn sẽ thích thú với câu chuyện này. Ngoài ra, hãy cùng đọc thêm các truyện đam mỹ khác như \"Vì Run Tay Nên Cộng Hết Điểm Vào Sắc Đẹp Rồi\" hay \"Xem Thường Ta? Ngài Đủ Khả Năng?\" để có những giây phút giải trí thú vị."}