{"name":"Trọng Sinh Tự Mang Thuốc Cho Mình","folder":"trongsinhtumangthuocchominh","tacGia":"Mạc Như Quy","theLoai":"Đô Thị","trangThai":"Đang ra","description":"Tác giả: Mạc Như Quy<br><br>Thể loại: Đô Thị, Trọng Sinh, Đam Mỹ<br><br>Giới thiệu:<br><br>Lưu Trưng một đời thật sự là não úng nước, ngu ngốc vô cùng, chính bản thân cũng không thể chịu được mình.<br><br>Vậy nên khi trọng sinh, Lưu Trưng quyết định phải khiến mình tỉnh táo lên, tìm lại bản thân trước kia, ép cậu ta đi uống thuốc.<br><br>\"Lưu Trưng, em không thích cô ấy, em yêu anh.\"<br><br>Đờ mờ!<br><br>Lưu Trưng buông lọ thuốc xuống, đi mở cửa: Tôi xuống lầu đổ rác."}