{"name":"Xuyên Không: Cha Con Tôi Đâu Rồi?","folder":"xuyenkhongchacontoidjauroi","tacGia":"Phồn Hoa Nhất Mộng","theLoai":"Ngôn Tình","trangThai":"Đang ra","description":"Bạn đang đọc truyện&nbsp;<b>Xuyên Không: Cha Con Tôi Đâu Rồi?</b>&nbsp;của tác giả&nbsp;<b>Phồn Hoa Nhất Mộng</b>. “Mẹ, Yên Yên đói quá.”<br><br>Trong một gian nhà tranh rách nát nơi thôn làng Đại Vĩ của Vương Triều Đại Lý, cô gái nhỏ ủy khuất quẹt quẹt miệng nói.<br><br>Lưu Ly nhìn cô nhóc như dân tị nạn châu Phi lại sở hữu một đôi mắt to trong veo như nước, bèn không nhịn được lại thở dài trong lòng.<br><br>Cô xuyên không thật rồi.<br><br>Cô đường đường là một dược sĩ thiên tài kiêm đại lão giấu mặt của đế quốc thương trường, xui xẻo thế nào lại bị một kẻ nhảy lầu tự sát nện trúng trên đường đi làm, xuyên không vào một thôn phụ cổ đại chưa kết hôn đã có con lại cùng tên cùng họ với cô, cô chưa từng yêu đương, đột nhiên lại thành mẹ của hai đứa trẻ.<br><br>Mà nguyên chủ vì nhường đồ ăn cho hai đứa nhỏ, thời gian dài uống nước qua ngày, nên cứ như vậy chết đói."}