{"name":"Chắp Vá Hạnh Phúc","folder":"chapvahanhphuc","tacGia":"Mập Mập7299","theLoai":"Ngôn Tình","trangThai":"Đang ra","description":"Bạn đang đọc truyện Chắp Vá Hạnh Phúc của tác giả Mập Mập7299. Vốn là một người không cha mẹ, tự mình trưởng thành, có một thân y thuật đủ dùng.<br><br>Chỉ là không ngờ ông trời trêu người, khi cô hái thuốc lại bị sét đánh.<br><br>Trong lúc tưởng mình đã chết, có cơ duyên khiến cô xuyên đến một thân thể khác, có điều, thân thể tên Sở Uyển này....<br><br>Đã có gia đình không nói, nhưng cuộc hôn nhân này chỉ là hình thức, đã có con trai nhưng lại suýt bóp chết thằng bé.<br><br>Sau này bị trầm cảm lại bị đưa sang Mỹ sinh hoạt.<br><br>Cô sẽ phải sống với thân phận Sở Uyển như thế nào?<br><br>Khi người chồng trên danh nghĩa của cô - Phó Cẩn là người đàn ông đa mưu túc trí, lạnh lùng, thâm trầm cùng đứa con - Phó Xuyên trầm cảm, tự bế, tự kỉ.<br><br>Ba người ba thái cực liệu có gắn kết lại cuộc hôn nhân sai lầm hay tan vỡ?<br><br>Nếu yêu thích truyện ngôn tình, bạn có thể đọc thêm Cô Vợ Ẩn Hôn Của Lục Thiếu hoặc Mạnh Mẽ Yêu Nhau 100 Ngày."}