{"name":"Dượng Tôi Biến Thành Mỹ Nam Rồi","folder":"duongtoibienthanhmynamroi","tacGia":"Boo","theLoai":"Ngôn Tình","trangThai":"Đang ra","description":"Tác giả: Boo<br><br>Thể loại: Ngôn Tình, Trinh Thám, Linh Dị, Huyền Huyễn<br><br>Giới thiệu:<br><br>Người thanh niên này là ai? Mọi người bị sao hết rồi? Thật là đáng sợ!...<br><br>Năm tôi 10 tuổi mẹ tái hôn với một người đàn ông trung niên, hai năm sau sinh ra em trai hiện giờ của tôi. Vì lý do công việc nên ông ta rất ít khi ở nhà, từ nhỏ tôi đã hiếm khi gặp mặt ông ta. NHƯNG, TÔI KHẲNG ĐỊNH. Chắc chắn một điều, người thanh niên trước mặt không phải ông ta.<br><br>Anh ta chỉ tầm hai mấy tuổi, bất quá ba mươi là cùng, làm sao có thể là một ông chú trung niên hơn 50 tuổi chứ. Bề ngoài, độ tuổi, chiều cao tất cả đều không phải người dượng này của tôi cơ mà.<br><br>Không ai cảm thấy điều này thật sự kì lạ sao? Có phải đều điên hết rồi không?"}