{"name":"Hoa Đào Nhỏ","folder":"hoadjaonho","tacGia":"Nguyên Chi Hề","theLoai":"Ngôn Tình","trangThai":"Full","description":"HOA ĐÀO NHỎ<br><br>Tác giả: Nguyên Chi Hề<br><br>Convert: Khóa luận tốt nghiệp được 9 điểm<br><br>Edit: Vườn Nhà Dâu + Leah<br><br>Thể loại: Ngôn tình, hiện đại, ngọt ngào, nhẹ nhàng, lãng mạn, nam chính bị câm, HE.<br><br>Số chương: 20 chương<br><br>Giới thiệu<br><br>Hứa Tư Đình thấp hơn Tống Lâm nửa cái đầu, vì vậy cô dựa hết vào người Tống Lâm, sau đó ngẩng đầu hỏi anh, “Tống Lâm, anh tới công viên bao giờ chưa?”<br><br>Anh lắc đầu, anh không thích chơi.<br><br>“Em cũng chỉ mới tới hai lần vào năm ngoái. Anh có dám chơi tàu lượn siêu tốc không?” Hứa Tư Đình rất thích đi tàu lượn siêu tốc, nhưng đi một người thì cô không dám, cần phải có người đi cùng mới được.<br><br>Anh lại lắc đầu, anh không biết.<br><br>“Không sao, nếu anh sợ thì kéo tay em, hoặc để em ngồi vòng quay ngựa gỗ với anh.” Trò này cũng được, hai người nắm tay, tiếng nhạc chầm chậm vang lên vô cùng lãng mạn.<br><br>Tống Lâm hôn lên trán cô, “Không cần phải lo cho anh, em muốn chơi gì thì anh chơi cùng em.”<br><br>“Như vậy sao được.” Hứa Tư Đình phản bác, “Anh là bạn trai em, đương nhiên là em phải lo cho anh rồi.”<br><br>Tim Tống Lâm bỗng đập lệch một nhịp, anh ôm chặt lấy cô, “Ừ, anh không sợ, em bảo vệ anh.”<br><br>“Vâng.”"}